ouster/cli/__init__.py
ouster/cli/py.typed
ouster/cli/plugins/testing.py
ouster/cli/plugins/source.py
ouster/cli/plugins/source_save.py
ouster/cli/plugins/source_sensor.py
ouster/cli/plugins/source_pcap.py
ouster/cli/plugins/source_localization.py
ouster/cli/plugins/source_util.py
ouster/cli/plugins/source_mapping.py
ouster/cli/plugins/source_osf.py
ouster/cli/plugins/discover.py
ouster/cli/plugins/source_bag.py
ouster/cli/core/cli_args.py
ouster/cli/core/util.py
ouster/cli/core/__init__.py
ouster/cli/core/borg.py
ouster/sdk/open_source.py
ouster/sdk/_bindings.cpython-310-x86_64-linux-gnu.so
ouster/sdk/__init__.py
ouster/sdk/py.typed
ouster/sdk/examples/viz_image_events.py
ouster/sdk/examples/reference.py
ouster/sdk/examples/osf.py
ouster/sdk/examples/pcap.py
ouster/sdk/examples/colormaps.py
ouster/sdk/examples/__init__.py
ouster/sdk/examples/client.py
ouster/sdk/examples/open3d_example.py
ouster/sdk/examples/lidar_scan.py
ouster/sdk/examples/viz.py
ouster/sdk/util/parsing.py
ouster/sdk/util/extrinsics.py
ouster/sdk/util/progress_bar.py
ouster/sdk/util/__init__.py
ouster/sdk/util/forward_slicer.py
ouster/sdk/util/pose_util.py
ouster/sdk/util/py.typed
ouster/sdk/util/metadata.py
ouster/sdk/bag/bag_packet_source.pyi
ouster/sdk/bag/__init__.py
ouster/sdk/bag/bag_packet_source.py
ouster/sdk/bag/bag_scan_source.py
ouster/sdk/bag/py.typed
ouster/sdk/pcap/packet_iter.py
ouster/sdk/pcap/pcap.py
ouster/sdk/pcap/__init__.py
ouster/sdk/pcap/py.typed
ouster/sdk/osf/multi.py
ouster/sdk/osf/__init__.py
ouster/sdk/osf/py.typed
ouster/sdk/mapping/kiss_slam.py
ouster/sdk/mapping/localization_backend.py
ouster/sdk/mapping/json_parser.py
ouster/sdk/mapping/slam_engine.py
ouster/sdk/mapping/util.py
ouster/sdk/mapping/__init__.py
ouster/sdk/mapping/requirements.json
ouster/sdk/mapping/kiss_localization.py
ouster/sdk/mapping/localization_engine.py
ouster/sdk/mapping/py.typed
ouster/sdk/mapping/ply_to_png.py
ouster_sdk-0.15.1.dist-info/METADATA
ouster_sdk-0.15.1.dist-info/RECORD
ouster_sdk-0.15.1.dist-info/top_level.txt
ouster_sdk-0.15.1.dist-info/entry_points.txt
ouster_sdk-0.15.1.dist-info/WHEEL
