Metadata-Version: 2.1
Name: ouster_sdk
Version: 0.15.1
Summary: Ouster Sensor SDK
Home-page: https://github.com/ouster-lidar/ouster-sdk
Author: Ouster Sensor SDK Developers
Author-email: oss@ouster.io
License: BSD 3-Clause License
Project-URL: Ouster SDK Documentation, https://static.ouster.dev/sdk-docs/index.html
Project-URL: Bug Tracker, https://github.com/ouster-lidar/ouster-sdk/issues
Project-URL: Ouster Customer Support, https://ouster.atlassian.net/servicedesk/customer/portal/8
Classifier: Development Status :: 3 - Alpha
Classifier: Intended Audience :: Developers
Classifier: Intended Audience :: Education
Classifier: Intended Audience :: Science/Research
Classifier: Operating System :: MacOS
Classifier: Operating System :: Microsoft :: Windows
Classifier: Operating System :: POSIX
Classifier: Operating System :: Unix
Classifier: Programming Language :: Python
Classifier: Programming Language :: Python :: 3
Classifier: Programming Language :: Python :: 3 :: Only
Classifier: Programming Language :: Python :: 3.8
Classifier: Programming Language :: Python :: 3.9
Classifier: Programming Language :: Python :: 3.10
Classifier: Programming Language :: Python :: 3.11
Classifier: Programming Language :: Python :: 3.12
Classifier: Topic :: Software Development :: Libraries
Classifier: Topic :: System :: Hardware :: Hardware Drivers
Classifier: Topic :: Scientific/Engineering
Classifier: Topic :: Scientific/Engineering :: Image Processing
Requires-Python: >=3.8, <4
Requires-Dist: psutil<6,>=5.9.5
Requires-Dist: zeroconf>=0.131.0
Requires-Dist: click<8.2.0,>=8.1.3
Requires-Dist: importlib-metadata==6.6.0
Requires-Dist: prettytable>=2.1.0
Requires-Dist: requests<3,>=2.0
Requires-Dist: more-itertools>=8.6
Requires-Dist: numpy!=1.19.4,>=1.19
Requires-Dist: laspy<3,>=2.5.0
Requires-Dist: threadpoolctl>=3.5.0
Requires-Dist: Pillow>=9.2
Requires-Dist: packaging
Requires-Dist: rosbags==0.9.23
Requires-Dist: kiss-icp==1.2.2; (platform_system == "Windows" and platform_machine == "AMD64") or (platform_system == "Linux" and platform_machine == "x86_64") or (platform_system == "Darwin" and platform_machine == "arm64")
Requires-Dist: scipy<2,>=1.7; platform_system != "Darwin" or platform_machine != "arm64"
Requires-Dist: setuptools; python_version >= "3.12"
Provides-Extra: dev
Requires-Dist: flake8; extra == "dev"
Requires-Dist: mypy; extra == "dev"
Requires-Dist: pylsp-mypy; extra == "dev"
Requires-Dist: python-lsp-server; extra == "dev"
Requires-Dist: yapf; extra == "dev"
Provides-Extra: docs
Requires-Dist: Sphinx>=3.5; extra == "docs"
Requires-Dist: sphinx-autodoc-typehints==1.17.0; extra == "docs"
Requires-Dist: sphinx-rtd-theme==1.0.0; extra == "docs"
Requires-Dist: sphinx-copybutton==0.5.0; extra == "docs"
Requires-Dist: docutils<0.18; extra == "docs"
Requires-Dist: sphinx-tabs==3.3.1; extra == "docs"
Requires-Dist: breathe==4.33.1; extra == "docs"
Requires-Dist: sphinx-rtd-size; extra == "docs"
Provides-Extra: examples
Requires-Dist: matplotlib; extra == "examples"
Requires-Dist: opencv-python; extra == "examples"
Requires-Dist: laspy; extra == "examples"
Requires-Dist: PyQt5; platform_system == "Windows" and extra == "examples"
Provides-Extra: test
Requires-Dist: pytest<8,>=7.0; extra == "test"
Requires-Dist: pytest-asyncio; extra == "test"
